distribution_probability_np/Binomialdistribution.py
distribution_probability_np/Gaussiandistribution.py
distribution_probability_np/Generaldistribution.py
distribution_probability_np/__init__.py
distribution_probability_np-0.3.dist-info/METADATA
distribution_probability_np-0.3.dist-info/WHEEL
distribution_probability_np-0.3.dist-info/top_level.txt
distribution_probability_np-0.3.dist-info/RECORD
