Metadata-Version: 2.1
Name: distribution_probability_np
Version: 0.3
Summary: Gaussian and Binomial distributions
